{
    "General": {
        "Title": "품목 분류 조회",
        "PageApi": "slip-search-page"
    },

    "QueryVars": {
        "QueryName": "shop/item-taxo"
    },

    "//SlipSearchFields": "쿼리를 공통하기 위한 테이블 필드변수들",
    "SlipSearchFields": {
        "SlipDateField": "",
        "SlipNoField": "item_taxo_no"
    },

    "//FormVars": "ListVars[0]-Caption",
    "FormVars": [
        {
            "DateRange": "",
            "DateNavi": "",
            "Date": "",
            "QuerySpeed": "표시속도",
            "SlipNo": "품목분류 번호",
            "CompanyName": "",
            "ItemCode": "",
            "FilterOption": "",
            "SimpleOption": ""
        }
    ],

    "// DateRangeOptions": "월:현재월의 1~30, 분기: 현재분기의 첫째월 1일 ~ 마지막월의 말일, 반기/년 동일한 컨셉,전체:1990~3000",
    "DateRangeOptions": [
        {
            "Value": "day",
            "Caption": "일"
        },
        {
            "Value": "week",
            "Caption": "주"
        },
        {
            "Value": "month",
            "Caption": "월"
        },
        {
            "Value": "quarterly",
            "Caption": "분기"
        },
        {
            "Value": "semiannual",
            "Caption": "반기"
        },
        {
            "Value": "year",
            "Caption": "년"
        },
        {
            "Value": "all",
            "Caption": "전체"
        }
    ],

    "QuerySpeedOptions": [
        {
            "Value": "quick",
            "Caption": "빠르게"
        }
    ],
    "// OrderByOptions": "OrderBy Options//첫번째 Value가 Default",
    "OrderByOptions": [
        {
            "Value": "item_taxo_no desc",
            "Caption": "품목 분류 번호 역순"
        },
        {
            "Value": "item_taxo_no asc",
            "Caption": "품목 분류 번호 정렬"
        },
        {
            "Value": "company_name asc",
            "Caption": "업체명 정렬"
        },
        {
            "Value": "company_name desc",
            "Caption": "업체명 역순"
        },
        {
            "Value": "item_code asc",
            "Caption": "품목코드 정렬"
        },
        {
            "Value": "item_code desc",
            "Caption": "품목코드 역순"
        }
    ],

    "// ListVars": "ListVars[0]-caption, ListVars[2]-size(%), ListVars[3]-align",
    "ListVars": [
        {
            "No": "번호",
            "SlipNo": "품목분류 위젯번호",
            "DealCode": "",
            "Company": "품목분류 위젯명",
            "SetGroup": "작성자",
            "Item": "",
            "Amt": "합계 금액",
            "Status": "상황",
            "Ref": "담당부서"
        },
        {
            "No": "6",
            "SlipNo": "13",
            "DealCode": "13",
            "Company": "13",
            "SetGroup": "10",
            "Item": "35",
            "Amt": "0",
            "Status": "0",
            "Ref": "10"
        },
        {
            "No": "center",
            "SlipNo": "left",
            "DealCode": "deal_type('deal-type')",
            "Company": "left",
            "SetGroup": "left",
            "Item": "left",
            "Amt": "decimal('purch_amt')",
            "Status": "left",
            "Ref": "left"
        }
    ]
}
